[
   {
      "archived" : false,
      "column_url" : "https://api.github.com/projects/columns/10252135",
      "created_at" : "2020-08-14T16:30:51Z",
      "creator" : {
         "avatar_url" : "https://avatars.githubusercontent.com/u/11927855?u=546cffaaec97b1bd129b8d5023c008dfde2f1043&v=4",
         "events_url" : "https://api.github.com/users/XerTheSquirrel/events{/privacy}",
         "followers_url" : "https://api.github.com/users/XerTheSquirrel/followers",
         "following_url" : "https://api.github.com/users/XerTheSquirrel/following{/other_user}",
         "gists_url" : "https://api.github.com/users/XerTheSquirrel/gists{/gist_id}",
         "gravatar_id" : "",
         "html_url" : "https://github.com/XerTheSquirrel",
         "id" : 11927855,
         "login" : "XerTheSquirrel",
         "node_id" : "MDQ6VXNlcjExOTI3ODU1",
         "organizations_url" : "https://api.github.com/users/XerTheSquirrel/orgs",
         "received_events_url" : "https://api.github.com/users/XerTheSquirrel/received_events",
         "repos_url" : "https://api.github.com/users/XerTheSquirrel/repos",
         "site_admin" : false,
         "starred_url" : "https://api.github.com/users/XerTheSquirrel/starred{/owner}{/repo}",
         "subscriptions_url" : "https://api.github.com/users/XerTheSquirrel/subscriptions",
         "type" : "User",
         "url" : "https://api.github.com/users/XerTheSquirrel"
      },
      "id" : 43677407,
      "node_id" : "MDExOlByb2plY3RDYXJkNDM2Nzc0MDc=",
      "note" : "Await completion of https://github.com/SquirrelJME/SquirrelJME/projects/48 .",
      "project_url" : "https://api.github.com/projects/5093020",
      "updated_at" : "2020-08-14T16:30:51Z",
      "url" : "https://api.github.com/projects/columns/cards/43677407"
   },
   {
      "archived" : false,
      "column_url" : "https://api.github.com/projects/columns/10252135",
      "created_at" : "2020-08-01T04:03:50Z",
      "creator" : {
         "avatar_url" : "https://avatars.githubusercontent.com/u/11927855?u=546cffaaec97b1bd129b8d5023c008dfde2f1043&v=4",
         "events_url" : "https://api.github.com/users/XerTheSquirrel/events{/privacy}",
         "followers_url" : "https://api.github.com/users/XerTheSquirrel/followers",
         "following_url" : "https://api.github.com/users/XerTheSquirrel/following{/other_user}",
         "gists_url" : "https://api.github.com/users/XerTheSquirrel/gists{/gist_id}",
         "gravatar_id" : "",
         "html_url" : "https://github.com/XerTheSquirrel",
         "id" : 11927855,
         "login" : "XerTheSquirrel",
         "node_id" : "MDQ6VXNlcjExOTI3ODU1",
         "organizations_url" : "https://api.github.com/users/XerTheSquirrel/orgs",
         "received_events_url" : "https://api.github.com/users/XerTheSquirrel/received_events",
         "repos_url" : "https://api.github.com/users/XerTheSquirrel/repos",
         "site_admin" : false,
         "starred_url" : "https://api.github.com/users/XerTheSquirrel/starred{/owner}{/repo}",
         "subscriptions_url" : "https://api.github.com/users/XerTheSquirrel/subscriptions",
         "type" : "User",
         "url" : "https://api.github.com/users/XerTheSquirrel"
      },
      "id" : 42909324,
      "node_id" : "MDExOlByb2plY3RDYXJkNDI5MDkzMjQ=",
      "note" : "GCF PPP (SquirrelJME Special).",
      "project_url" : "https://api.github.com/projects/5093020",
      "updated_at" : "2020-08-01T04:03:50Z",
      "url" : "https://api.github.com/projects/columns/cards/42909324"
   },
   {
      "archived" : false,
      "column_url" : "https://api.github.com/projects/columns/10252135",
      "created_at" : "2020-08-01T04:03:42Z",
      "creator" : {
         "avatar_url" : "https://avatars.githubusercontent.com/u/11927855?u=546cffaaec97b1bd129b8d5023c008dfde2f1043&v=4",
         "events_url" : "https://api.github.com/users/XerTheSquirrel/events{/privacy}",
         "followers_url" : "https://api.github.com/users/XerTheSquirrel/followers",
         "following_url" : "https://api.github.com/users/XerTheSquirrel/following{/other_user}",
         "gists_url" : "https://api.github.com/users/XerTheSquirrel/gists{/gist_id}",
         "gravatar_id" : "",
         "html_url" : "https://github.com/XerTheSquirrel",
         "id" : 11927855,
         "login" : "XerTheSquirrel",
         "node_id" : "MDQ6VXNlcjExOTI3ODU1",
         "organizations_url" : "https://api.github.com/users/XerTheSquirrel/orgs",
         "received_events_url" : "https://api.github.com/users/XerTheSquirrel/received_events",
         "repos_url" : "https://api.github.com/users/XerTheSquirrel/repos",
         "site_admin" : false,
         "starred_url" : "https://api.github.com/users/XerTheSquirrel/starred{/owner}{/repo}",
         "subscriptions_url" : "https://api.github.com/users/XerTheSquirrel/subscriptions",
         "type" : "User",
         "url" : "https://api.github.com/users/XerTheSquirrel"
      },
      "id" : 42909320,
      "node_id" : "MDExOlByb2plY3RDYXJkNDI5MDkzMjA=",
      "note" : "GCF Layering (SquirrelJME Special, would allow for example PPP over modems?).",
      "project_url" : "https://api.github.com/projects/5093020",
      "updated_at" : "2020-08-01T04:03:42Z",
      "url" : "https://api.github.com/projects/columns/cards/42909320"
   },
   {
      "archived" : false,
      "column_url" : "https://api.github.com/projects/columns/10252135",
      "created_at" : "2020-08-01T04:03:10Z",
      "creator" : {
         "avatar_url" : "https://avatars.githubusercontent.com/u/11927855?u=546cffaaec97b1bd129b8d5023c008dfde2f1043&v=4",
         "events_url" : "https://api.github.com/users/XerTheSquirrel/events{/privacy}",
         "followers_url" : "https://api.github.com/users/XerTheSquirrel/followers",
         "following_url" : "https://api.github.com/users/XerTheSquirrel/following{/other_user}",
         "gists_url" : "https://api.github.com/users/XerTheSquirrel/gists{/gist_id}",
         "gravatar_id" : "",
         "html_url" : "https://github.com/XerTheSquirrel",
         "id" : 11927855,
         "login" : "XerTheSquirrel",
         "node_id" : "MDQ6VXNlcjExOTI3ODU1",
         "organizations_url" : "https://api.github.com/users/XerTheSquirrel/orgs",
         "received_events_url" : "https://api.github.com/users/XerTheSquirrel/received_events",
         "repos_url" : "https://api.github.com/users/XerTheSquirrel/repos",
         "site_admin" : false,
         "starred_url" : "https://api.github.com/users/XerTheSquirrel/starred{/owner}{/repo}",
         "subscriptions_url" : "https://api.github.com/users/XerTheSquirrel/subscriptions",
         "type" : "User",
         "url" : "https://api.github.com/users/XerTheSquirrel"
      },
      "id" : 42909308,
      "node_id" : "MDExOlByb2plY3RDYXJkNDI5MDkzMDg=",
      "note" : "GCF Serial (SquirrelJME Special).",
      "project_url" : "https://api.github.com/projects/5093020",
      "updated_at" : "2020-08-01T04:03:10Z",
      "url" : "https://api.github.com/projects/columns/cards/42909308"
   },
   {
      "archived" : false,
      "column_url" : "https://api.github.com/projects/columns/10252135",
      "created_at" : "2020-08-01T04:01:27Z",
      "creator" : {
         "avatar_url" : "https://avatars.githubusercontent.com/u/11927855?u=546cffaaec97b1bd129b8d5023c008dfde2f1043&v=4",
         "events_url" : "https://api.github.com/users/XerTheSquirrel/events{/privacy}",
         "followers_url" : "https://api.github.com/users/XerTheSquirrel/followers",
         "following_url" : "https://api.github.com/users/XerTheSquirrel/following{/other_user}",
         "gists_url" : "https://api.github.com/users/XerTheSquirrel/gists{/gist_id}",
         "gravatar_id" : "",
         "html_url" : "https://github.com/XerTheSquirrel",
         "id" : 11927855,
         "login" : "XerTheSquirrel",
         "node_id" : "MDQ6VXNlcjExOTI3ODU1",
         "organizations_url" : "https://api.github.com/users/XerTheSquirrel/orgs",
         "received_events_url" : "https://api.github.com/users/XerTheSquirrel/received_events",
         "repos_url" : "https://api.github.com/users/XerTheSquirrel/repos",
         "site_admin" : false,
         "starred_url" : "https://api.github.com/users/XerTheSquirrel/starred{/owner}{/repo}",
         "subscriptions_url" : "https://api.github.com/users/XerTheSquirrel/subscriptions",
         "type" : "User",
         "url" : "https://api.github.com/users/XerTheSquirrel"
      },
      "id" : 42909276,
      "node_id" : "MDExOlByb2plY3RDYXJkNDI5MDkyNzY=",
      "note" : "GCF HTTP",
      "project_url" : "https://api.github.com/projects/5093020",
      "updated_at" : "2020-08-01T04:01:27Z",
      "url" : "https://api.github.com/projects/columns/cards/42909276"
   },
   {
      "archived" : false,
      "column_url" : "https://api.github.com/projects/columns/10252135",
      "created_at" : "2020-08-01T04:01:18Z",
      "creator" : {
         "avatar_url" : "https://avatars.githubusercontent.com/u/11927855?u=546cffaaec97b1bd129b8d5023c008dfde2f1043&v=4",
         "events_url" : "https://api.github.com/users/XerTheSquirrel/events{/privacy}",
         "followers_url" : "https://api.github.com/users/XerTheSquirrel/followers",
         "following_url" : "https://api.github.com/users/XerTheSquirrel/following{/other_user}",
         "gists_url" : "https://api.github.com/users/XerTheSquirrel/gists{/gist_id}",
         "gravatar_id" : "",
         "html_url" : "https://github.com/XerTheSquirrel",
         "id" : 11927855,
         "login" : "XerTheSquirrel",
         "node_id" : "MDQ6VXNlcjExOTI3ODU1",
         "organizations_url" : "https://api.github.com/users/XerTheSquirrel/orgs",
         "received_events_url" : "https://api.github.com/users/XerTheSquirrel/received_events",
         "repos_url" : "https://api.github.com/users/XerTheSquirrel/repos",
         "site_admin" : false,
         "starred_url" : "https://api.github.com/users/XerTheSquirrel/starred{/owner}{/repo}",
         "subscriptions_url" : "https://api.github.com/users/XerTheSquirrel/subscriptions",
         "type" : "User",
         "url" : "https://api.github.com/users/XerTheSquirrel"
      },
      "id" : 42909269,
      "node_id" : "MDExOlByb2plY3RDYXJkNDI5MDkyNjk=",
      "note" : "GCF SSL.",
      "project_url" : "https://api.github.com/projects/5093020",
      "updated_at" : "2020-08-01T04:01:18Z",
      "url" : "https://api.github.com/projects/columns/cards/42909269"
   },
   {
      "archived" : false,
      "column_url" : "https://api.github.com/projects/columns/10252135",
      "created_at" : "2020-08-01T04:00:59Z",
      "creator" : {
         "avatar_url" : "https://avatars.githubusercontent.com/u/11927855?u=546cffaaec97b1bd129b8d5023c008dfde2f1043&v=4",
         "events_url" : "https://api.github.com/users/XerTheSquirrel/events{/privacy}",
         "followers_url" : "https://api.github.com/users/XerTheSquirrel/followers",
         "following_url" : "https://api.github.com/users/XerTheSquirrel/following{/other_user}",
         "gists_url" : "https://api.github.com/users/XerTheSquirrel/gists{/gist_id}",
         "gravatar_id" : "",
         "html_url" : "https://github.com/XerTheSquirrel",
         "id" : 11927855,
         "login" : "XerTheSquirrel",
         "node_id" : "MDQ6VXNlcjExOTI3ODU1",
         "organizations_url" : "https://api.github.com/users/XerTheSquirrel/orgs",
         "received_events_url" : "https://api.github.com/users/XerTheSquirrel/received_events",
         "repos_url" : "https://api.github.com/users/XerTheSquirrel/repos",
         "site_admin" : false,
         "starred_url" : "https://api.github.com/users/XerTheSquirrel/starred{/owner}{/repo}",
         "subscriptions_url" : "https://api.github.com/users/XerTheSquirrel/subscriptions",
         "type" : "User",
         "url" : "https://api.github.com/users/XerTheSquirrel"
      },
      "id" : 42909262,
      "node_id" : "MDExOlByb2plY3RDYXJkNDI5MDkyNjI=",
      "note" : "GCF Modems, base on GCF and DIO.",
      "project_url" : "https://api.github.com/projects/5093020",
      "updated_at" : "2020-08-01T04:00:59Z",
      "url" : "https://api.github.com/projects/columns/cards/42909262"
   },
   {
      "archived" : false,
      "column_url" : "https://api.github.com/projects/columns/10252135",
      "created_at" : "2020-08-01T04:00:33Z",
      "creator" : {
         "avatar_url" : "https://avatars.githubusercontent.com/u/11927855?u=546cffaaec97b1bd129b8d5023c008dfde2f1043&v=4",
         "events_url" : "https://api.github.com/users/XerTheSquirrel/events{/privacy}",
         "followers_url" : "https://api.github.com/users/XerTheSquirrel/followers",
         "following_url" : "https://api.github.com/users/XerTheSquirrel/following{/other_user}",
         "gists_url" : "https://api.github.com/users/XerTheSquirrel/gists{/gist_id}",
         "gravatar_id" : "",
         "html_url" : "https://github.com/XerTheSquirrel",
         "id" : 11927855,
         "login" : "XerTheSquirrel",
         "node_id" : "MDQ6VXNlcjExOTI3ODU1",
         "organizations_url" : "https://api.github.com/users/XerTheSquirrel/orgs",
         "received_events_url" : "https://api.github.com/users/XerTheSquirrel/received_events",
         "repos_url" : "https://api.github.com/users/XerTheSquirrel/repos",
         "site_admin" : false,
         "starred_url" : "https://api.github.com/users/XerTheSquirrel/starred{/owner}{/repo}",
         "subscriptions_url" : "https://api.github.com/users/XerTheSquirrel/subscriptions",
         "type" : "User",
         "url" : "https://api.github.com/users/XerTheSquirrel"
      },
      "id" : 42909251,
      "node_id" : "MDExOlByb2plY3RDYXJkNDI5MDkyNTE=",
      "note" : "GCF IP Networking.",
      "project_url" : "https://api.github.com/projects/5093020",
      "updated_at" : "2020-08-01T04:01:52Z",
      "url" : "https://api.github.com/projects/columns/cards/42909251"
   },
   {
      "archived" : false,
      "column_url" : "https://api.github.com/projects/columns/10252135",
      "created_at" : "2020-08-01T04:00:29Z",
      "creator" : {
         "avatar_url" : "https://avatars.githubusercontent.com/u/11927855?u=546cffaaec97b1bd129b8d5023c008dfde2f1043&v=4",
         "events_url" : "https://api.github.com/users/XerTheSquirrel/events{/privacy}",
         "followers_url" : "https://api.github.com/users/XerTheSquirrel/followers",
         "following_url" : "https://api.github.com/users/XerTheSquirrel/following{/other_user}",
         "gists_url" : "https://api.github.com/users/XerTheSquirrel/gists{/gist_id}",
         "gravatar_id" : "",
         "html_url" : "https://github.com/XerTheSquirrel",
         "id" : 11927855,
         "login" : "XerTheSquirrel",
         "node_id" : "MDQ6VXNlcjExOTI3ODU1",
         "organizations_url" : "https://api.github.com/users/XerTheSquirrel/orgs",
         "received_events_url" : "https://api.github.com/users/XerTheSquirrel/received_events",
         "repos_url" : "https://api.github.com/users/XerTheSquirrel/repos",
         "site_admin" : false,
         "starred_url" : "https://api.github.com/users/XerTheSquirrel/starred{/owner}{/repo}",
         "subscriptions_url" : "https://api.github.com/users/XerTheSquirrel/subscriptions",
         "type" : "User",
         "url" : "https://api.github.com/users/XerTheSquirrel"
      },
      "id" : 42909250,
      "node_id" : "MDExOlByb2plY3RDYXJkNDI5MDkyNTA=",
      "note" : "GCF IMC.",
      "project_url" : "https://api.github.com/projects/5093020",
      "updated_at" : "2020-08-01T04:00:29Z",
      "url" : "https://api.github.com/projects/columns/cards/42909250"
   },
   {
      "archived" : false,
      "column_url" : "https://api.github.com/projects/columns/10252135",
      "created_at" : "2020-08-01T04:00:23Z",
      "creator" : {
         "avatar_url" : "https://avatars.githubusercontent.com/u/11927855?u=546cffaaec97b1bd129b8d5023c008dfde2f1043&v=4",
         "events_url" : "https://api.github.com/users/XerTheSquirrel/events{/privacy}",
         "followers_url" : "https://api.github.com/users/XerTheSquirrel/followers",
         "following_url" : "https://api.github.com/users/XerTheSquirrel/following{/other_user}",
         "gists_url" : "https://api.github.com/users/XerTheSquirrel/gists{/gist_id}",
         "gravatar_id" : "",
         "html_url" : "https://github.com/XerTheSquirrel",
         "id" : 11927855,
         "login" : "XerTheSquirrel",
         "node_id" : "MDQ6VXNlcjExOTI3ODU1",
         "organizations_url" : "https://api.github.com/users/XerTheSquirrel/orgs",
         "received_events_url" : "https://api.github.com/users/XerTheSquirrel/received_events",
         "repos_url" : "https://api.github.com/users/XerTheSquirrel/repos",
         "site_admin" : false,
         "starred_url" : "https://api.github.com/users/XerTheSquirrel/starred{/owner}{/repo}",
         "subscriptions_url" : "https://api.github.com/users/XerTheSquirrel/subscriptions",
         "type" : "User",
         "url" : "https://api.github.com/users/XerTheSquirrel"
      },
      "id" : 42909249,
      "node_id" : "MDExOlByb2plY3RDYXJkNDI5MDkyNDk=",
      "note" : "GCF File.",
      "project_url" : "https://api.github.com/projects/5093020",
      "updated_at" : "2020-08-01T04:00:23Z",
      "url" : "https://api.github.com/projects/columns/cards/42909249"
   }
]
