[
   {
      "archived" : false,
      "column_url" : "https://api.github.com/projects/columns/4161094",
      "created_at" : "2020-01-21T15:12:16Z",
      "creator" : {
         "avatar_url" : "https://avatars.githubusercontent.com/u/11927855?u=546cffaaec97b1bd129b8d5023c008dfde2f1043&v=4",
         "events_url" : "https://api.github.com/users/XerTheSquirrel/events{/privacy}",
         "followers_url" : "https://api.github.com/users/XerTheSquirrel/followers",
         "following_url" : "https://api.github.com/users/XerTheSquirrel/following{/other_user}",
         "gists_url" : "https://api.github.com/users/XerTheSquirrel/gists{/gist_id}",
         "gravatar_id" : "",
         "html_url" : "https://github.com/XerTheSquirrel",
         "id" : 11927855,
         "login" : "XerTheSquirrel",
         "node_id" : "MDQ6VXNlcjExOTI3ODU1",
         "organizations_url" : "https://api.github.com/users/XerTheSquirrel/orgs",
         "received_events_url" : "https://api.github.com/users/XerTheSquirrel/received_events",
         "repos_url" : "https://api.github.com/users/XerTheSquirrel/repos",
         "site_admin" : false,
         "starred_url" : "https://api.github.com/users/XerTheSquirrel/starred{/owner}{/repo}",
         "subscriptions_url" : "https://api.github.com/users/XerTheSquirrel/subscriptions",
         "type" : "User",
         "url" : "https://api.github.com/users/XerTheSquirrel"
      },
      "id" : 31944808,
      "node_id" : "MDExOlByb2plY3RDYXJkMzE5NDQ4MDg=",
      "note" : "Implement date and time classes.",
      "project_url" : "https://api.github.com/projects/2074659",
      "updated_at" : "2020-01-21T15:12:16Z",
      "url" : "https://api.github.com/projects/columns/cards/31944808"
   },
   {
      "archived" : false,
      "column_url" : "https://api.github.com/projects/columns/4161094",
      "created_at" : "2019-01-14T19:43:36Z",
      "creator" : {
         "avatar_url" : "https://avatars.githubusercontent.com/u/11927855?u=546cffaaec97b1bd129b8d5023c008dfde2f1043&v=4",
         "events_url" : "https://api.github.com/users/XerTheSquirrel/events{/privacy}",
         "followers_url" : "https://api.github.com/users/XerTheSquirrel/followers",
         "following_url" : "https://api.github.com/users/XerTheSquirrel/following{/other_user}",
         "gists_url" : "https://api.github.com/users/XerTheSquirrel/gists{/gist_id}",
         "gravatar_id" : "",
         "html_url" : "https://github.com/XerTheSquirrel",
         "id" : 11927855,
         "login" : "XerTheSquirrel",
         "node_id" : "MDQ6VXNlcjExOTI3ODU1",
         "organizations_url" : "https://api.github.com/users/XerTheSquirrel/orgs",
         "received_events_url" : "https://api.github.com/users/XerTheSquirrel/received_events",
         "repos_url" : "https://api.github.com/users/XerTheSquirrel/repos",
         "site_admin" : false,
         "starred_url" : "https://api.github.com/users/XerTheSquirrel/starred{/owner}{/repo}",
         "subscriptions_url" : "https://api.github.com/users/XerTheSquirrel/subscriptions",
         "type" : "User",
         "url" : "https://api.github.com/users/XerTheSquirrel"
      },
      "id" : 16509857,
      "node_id" : "MDExOlByb2plY3RDYXJkMTY1MDk4NTc=",
      "note" : "https://github.com/XerTheSquirrel/SquirrelJME/projects/6",
      "project_url" : "https://api.github.com/projects/2074659",
      "updated_at" : "2019-01-14T19:43:39Z",
      "url" : "https://api.github.com/projects/columns/cards/16509857"
   },
   {
      "archived" : false,
      "column_url" : "https://api.github.com/projects/columns/4161094",
      "content_url" : "https://api.github.com/repos/SquirrelJME/SquirrelJME/issues/85",
      "created_at" : "2020-08-08T12:48:43Z",
      "creator" : {
         "avatar_url" : "https://avatars.githubusercontent.com/u/11927855?u=546cffaaec97b1bd129b8d5023c008dfde2f1043&v=4",
         "events_url" : "https://api.github.com/users/XerTheSquirrel/events{/privacy}",
         "followers_url" : "https://api.github.com/users/XerTheSquirrel/followers",
         "following_url" : "https://api.github.com/users/XerTheSquirrel/following{/other_user}",
         "gists_url" : "https://api.github.com/users/XerTheSquirrel/gists{/gist_id}",
         "gravatar_id" : "",
         "html_url" : "https://github.com/XerTheSquirrel",
         "id" : 11927855,
         "login" : "XerTheSquirrel",
         "node_id" : "MDQ6VXNlcjExOTI3ODU1",
         "organizations_url" : "https://api.github.com/users/XerTheSquirrel/orgs",
         "received_events_url" : "https://api.github.com/users/XerTheSquirrel/received_events",
         "repos_url" : "https://api.github.com/users/XerTheSquirrel/repos",
         "site_admin" : false,
         "starred_url" : "https://api.github.com/users/XerTheSquirrel/starred{/owner}{/repo}",
         "subscriptions_url" : "https://api.github.com/users/XerTheSquirrel/subscriptions",
         "type" : "User",
         "url" : "https://api.github.com/users/XerTheSquirrel"
      },
      "id" : 43313714,
      "node_id" : "MDExOlByb2plY3RDYXJkNDMzMTM3MTQ=",
      "note" : null,
      "project_url" : "https://api.github.com/projects/2074659",
      "updated_at" : "2021-04-22T00:20:02Z",
      "url" : "https://api.github.com/projects/columns/cards/43313714"
   },
   {
      "archived" : false,
      "column_url" : "https://api.github.com/projects/columns/4161094",
      "content_url" : "https://api.github.com/repos/SquirrelJME/SquirrelJME/issues/70",
      "created_at" : "2021-03-07T14:43:19Z",
      "creator" : {
         "avatar_url" : "https://avatars.githubusercontent.com/u/11927855?u=546cffaaec97b1bd129b8d5023c008dfde2f1043&v=4",
         "events_url" : "https://api.github.com/users/XerTheSquirrel/events{/privacy}",
         "followers_url" : "https://api.github.com/users/XerTheSquirrel/followers",
         "following_url" : "https://api.github.com/users/XerTheSquirrel/following{/other_user}",
         "gists_url" : "https://api.github.com/users/XerTheSquirrel/gists{/gist_id}",
         "gravatar_id" : "",
         "html_url" : "https://github.com/XerTheSquirrel",
         "id" : 11927855,
         "login" : "XerTheSquirrel",
         "node_id" : "MDQ6VXNlcjExOTI3ODU1",
         "organizations_url" : "https://api.github.com/users/XerTheSquirrel/orgs",
         "received_events_url" : "https://api.github.com/users/XerTheSquirrel/received_events",
         "repos_url" : "https://api.github.com/users/XerTheSquirrel/repos",
         "site_admin" : false,
         "starred_url" : "https://api.github.com/users/XerTheSquirrel/starred{/owner}{/repo}",
         "subscriptions_url" : "https://api.github.com/users/XerTheSquirrel/subscriptions",
         "type" : "User",
         "url" : "https://api.github.com/users/XerTheSquirrel"
      },
      "id" : 56360040,
      "node_id" : "MDExOlByb2plY3RDYXJkNTYzNjAwNDA=",
      "note" : null,
      "project_url" : "https://api.github.com/projects/2074659",
      "updated_at" : "2023-07-29T19:54:29Z",
      "url" : "https://api.github.com/projects/columns/cards/56360040"
   }
]
